COPYING
MANIFEST.in
README.md
setup.py
fluent/__init__.py
fluent/event.py
fluent/handler.py
fluent/sender.py
fluent_logger_pyramid.egg-info/PKG-INFO
fluent_logger_pyramid.egg-info/SOURCES.txt
fluent_logger_pyramid.egg-info/dependency_links.txt
fluent_logger_pyramid.egg-info/requires.txt
fluent_logger_pyramid.egg-info/top_level.txt