Metadata-Version: 1.1
Name: fluent-logger-pyramid
Version: 0.0.3
Summary: A Python logging handler for Fluentd, with better Pyramid integration
Home-page: https://github.com/nashyeung/fluent-logger-pyramid
Author: Nash Yeung
Author-email: nashyeung@gmail.com
License: Apache License, Version 2.0
Download-URL: http://pypi.python.org/pypi/fluent-logger-pyramid/
Platform: UNKNOWN
Classifier: Programming Language :: Python :: 2
Classifier: Programming Language :: Python :: 3
Classifier: Development Status :: 4 - Beta
Classifier: Intended Audience :: Developers
